<?xml version="1.0" encoding="UTF-8"?>
<tls:ann xmlns="http://www.tei-c.org/ns/1.0" xmlns:tls="http://hxwd.org/ns/1.0" concept="PROBABLE" concept-id="uuid-cc26ca83-0ac3-4ff6-a1e8-a183960424d7" xml:id="uuid-05cf5e64-d401-4d32-8f5e-64d401cd32e9">
    <link target="#KR1e0001_tls_005-303a.13 #uuid-b2651eeb-f3f3-460a-91b9-d24b8cba6f1c"/>
    <tls:text>
        <tls:srcline title="春秋左傳" target="#KR1e0001_tls_005-303a.13" pos="3">天其或者欲使衛討邢乎？」</tls:srcline>
        <tls:line title="春秋左傳 (en)" src="Legge">May not Heaven be wishing to employ Wèi to punish Xíng?"</tls:line>
    </tls:text>
    <form corresp="#uuid-7be571ca-f00b-41c6-b5eb-2c0b43e6bcd8 #uuid-638f5102-6260-4085-891d-9864102bc27c" orig="或者">
        <orth>或者</orth>
        <pron xml:lang="zh-Latn-x-pinyin">huò zhě</pron>
    </form>
    <sense corresp="#uuid-b2651eeb-f3f3-460a-91b9-d24b8cba6f1c">
        <gramGrp>
                    <pos>P</pos>
  <tls:syn-func corresp="#uuid-e7f1e69d-7edf-4e5a-bdef-c5995d0fb79d">PPadS</tls:syn-func>
                    <usg type="warring-states-currency">2</usg>
                </gramGrp>
        <def>probably; presumably; I suppose..; conceivably; for all we know</def>
    </sense>
    <tls:metadata resp="#CH" created="2019-03-23T21:01:49.895+09:00">
        <respStmt>
            <resp>added</resp>
            <name>CH</name>
        </respStmt>
    </tls:metadata>
</tls:ann>