<?xml version="1.0" encoding="UTF-8"?>
<superEntry xmlns="http://www.tei-c.org/ns/1.0" xml:id="uuid-07340cee-0abe-475e-b40c-ee0abee75ee7" n="1">
    <form>
        <orth>權謀</orth>
    </form>
    <entry xmlns:tls="http://hxwd.org/ns/1.0" tls:concept="PLAN" tls:concept-id="uuid-8bed01e5-7f3e-47ee-8296-6f90c3f31f37" xml:id="uuid-1a22b9d1-6d6a-4589-b1b4-9e5543c763f4" n="10">
            <form corresp="#uuid-45ad686c-5637-4415-9838-f6fccab6e682 #uuid-bfa6623d-c65f-48cb-97e3-10c051108156">
                <orth>權謀</orth>
                <pron xml:lang="zh-Latn-x-pinyin">quán móu</pron>
                <pron xml:lang="zh-x-mc" resp="rec:baxter">gjwen mjuw</pron>
                <pron xml:lang="zh-x-oc" resp="rec:pan-wuyun">ɡron mɯ</pron>
            </form>
            <sense xml:id="uuid-3d8e881b-4369-403c-8fc9-14dc8796f9b8" resp="#dsehnal" tls:created="2019-12-17T06:33:26.054+09:00" n="2">
                <gramGrp>
                    <pos>N</pos>
                    <tls:syn-func corresp="#uuid-db0698e7-db2f-4ee3-9a20-0c2b2e0cebf0">NPab</tls:syn-func>
                    <tls:sem-feat corresp="#uuid-76a3454c-a084-47af-b1b2-9839a8900995">general</tls:sem-feat>
                </gramGrp>
                <def resp="#CH" updated="2022-09-21T18:05:40.011+09:00">(the art of) strategic planning in accordance with circumstances; plans of all kinds</def>
            </sense>
            <sense xml:id="uuid-bb6604c4-d6da-498b-9a28-0e0bb76a3bc9" resp="#CH" tls:created="2019-12-25T23:26:44.251+09:00" n="4">
                <gramGrp>
                    <pos>N</pos>
                    <tls:syn-func corresp="#uuid-db0698e7-db2f-4ee3-9a20-0c2b2e0cebf0">NPab</tls:syn-func>
                    <tls:sem-feat corresp="#uuid-f55cff2f-f0e3-4f08-a89c-5d08fcf3fe89">act</tls:sem-feat>
                </gramGrp>
                <def>negative: intrigues</def>
            </sense>
        <sense xml:id="uuid-a2fc0aed-eca5-4042-bc0a-edeca59042da" resp="#zadrapa" tls:created="2022-06-10T20:47:22.292+09:00" n="4">
            <gramGrp>
                <pos>V</pos>
                <tls:syn-func corresp="#uuid-091af450-64e0-4b82-98a2-84d0444b6d19">VPi</tls:syn-func>
            </gramGrp>
            <def>to plot</def>
        </sense>
    </entry>
</superEntry>