<?xml version="1.0" encoding="UTF-8"?>
<tls:ann xmlns="http://www.tei-c.org/ns/1.0" xmlns:tls="http://hxwd.org/ns/1.0" concept="LOVE" concept-id="uuid-298d9710-caa5-43f5-a9f7-85ca84e7815c" xml:id="uuid-98b0e57c-7a39-4639-b0e5-7c7a399639d6">
    <link target="#KR3c0001_tls_002-118a.7 #uuid-4fe937a6-ba84-4abc-a4c3-e7ec5eb2041f"/>
    <tls:text>
        <tls:srcline title="管子" target="#KR3c0001_tls_002-118a.7" pos="2">父慈子孝，</tls:srcline>
        <tls:line title="管子 (en)" src="Rickett, Princeton University Press">the compassion of fathers, the filial piety of sons,</tls:line>
    </tls:text>
    <form corresp="#uuid-a97a321d-5450-4629-b96a-12be84e3054e" orig="慈">
        <orth>慈</orth>
        <pron xml:lang="zh-Latn-x-pinyin">cí</pron>
    </form>
    <sense corresp="#uuid-4fe937a6-ba84-4abc-a4c3-e7ec5eb2041f">
        <gramGrp>
                    <pos>V</pos>
  <tls:syn-func corresp="#uuid-53cee9f8-4041-45e5-ae55-f0bfdec33a11">vt[oN]</tls:syn-func>
                    <usg type="warring-states-currency">4</usg>
                </gramGrp>
        <def>show loving kindness in action</def>
    </sense>
    <tls:metadata resp="#CH" created="2019-03-23T21:01:49.895+09:00">
        <respStmt>
            <resp>added</resp>
            <name>CH</name>
        </respStmt>
    </tls:metadata>
</tls:ann>