<?xml version="1.0" encoding="UTF-8"?>
<mods xmlns="http://www.loc.gov/mods/v3" xmlns:xlink="http://www.w3.org/1999/xlink" xmlns:xsi="http://www.w3.org/2001/XMLSchema-instance" ID="uuid-de60297d-fa9c-4dec-83cf-e012bf311207" version="3.6" xsi:schemaLocation="http://www.loc.gov/mods/v3 http://cluster-schemas.uni-hd.de/modsCluster.xsd">
<name type="personal">
<namePart type="given" lang="chi" transliteration="chinese/ala-lc" script="Latn">Baozhong</namePart>
<namePart type="family" lang="chi" transliteration="chinese/ala-lc" script="Latn">Yang</namePart>
<namePart type="given" lang="chi" script="Hant">寶忠</namePart>
<namePart type="family" lang="chi" script="Hant">楊</namePart>
<role>
<roleTerm type="text">author</roleTerm>
        </role>
    </name>
<name type="personal">
<namePart type="given" lang="chi" transliteration="chinese/ala-lc" script="Latn">Jinping</namePart>
<namePart type="family" lang="chi" transliteration="chinese/ala-lc" script="Latn">Ma</namePart>
<namePart type="given" lang="chi" script="Hant">金平</namePart>
<namePart type="family" lang="chi" script="Hant">馬</namePart>
<role>
<roleTerm type="text">author</roleTerm>
        </role>
    </name>
<titleInfo lang="chi" script="Hant">
<title>論衡訓詁資料纂輯</title>
    </titleInfo>
<originInfo>
<place>
<placeTerm type="text">Baoding</placeTerm>
        </place>
<publisher>Hebei Daxue Chubanshe</publisher>
<dateIssued encoding="w3cdtf">2002</dateIssued>
<issuance>monographic</issuance>
    </originInfo>
<typeOfResource>text</typeOfResource>
<genre authority="marcgt">book</genre>
<note type="bibliographic-reference">YANG BAOZHONG 2002</note>
<note type="ref-usage">0</note>
</mods>