<guangyun-entry xmlns="http://exist-db.org/tls" xmlns:mods="http://www.loc.gov/mods/v3" xmlns:xlink="http://www.w3.org/1999/xlink" xml:id="uuid-cdda521d-959a-45f8-8079-abd7216586fa">
<graphs>
<attested-graph>
<unemended-graph>
<graph>
</graph>
</unemended-graph>
<emended-graph>
<graph>
</graph>
</emended-graph>
<graph>溠
</graph>
</attested-graph>
<standardised-graph>
<graph>
</graph>
</standardised-graph>
</graphs>
<gloss>水名出義陽又側稼切
</gloss>
<xiaoyun>
<headword>樝
</headword>
<graph-count>12
</graph-count>
</xiaoyun>
<fanqie>
<fanqie-shangzi>
<fanqie-shangzi-attested>
<graph>側
</graph>
</fanqie-shangzi-attested>
<fanqie-shangzi-standard>
<graph>
</graph>
</fanqie-shangzi-standard>
</fanqie-shangzi>
<fanqie-xiazi>
<fanqie-xiazi-attested>
<graph>加
</graph>
</fanqie-xiazi-attested>
<fanqie-xiazi-standard>
<graph>
</graph>
</fanqie-xiazi-standard>
</fanqie-xiazi>
</fanqie>
<ids>
<guangyun-jiaoshi-id>6876
</guangyun-jiaoshi-id>
<pan-wuyun-id>6926
</pan-wuyun-id>
</ids>
<locations>
<guangyun-location>168.23
</guangyun-location>
<baxter-location>168.16
</baxter-location>
<pan-wuyun-location>148
</pan-wuyun-location>
</locations>
<pan-wuyun-note-on-guangyun>
</pan-wuyun-note-on-guangyun>
<pan-wuyun-note>
</pan-wuyun-note>
<pronunciation>
<mandarin>
<jin>zhā
</jin>
<wen>
</wen>
<yi>
</yi>
<bai>
</bai>
<jiu>
</jiu>
</mandarin>
<middle-chinese>
<categories>
<聲>莊
</聲>
<等>二
</等>
<呼>開
</呼>
<韻部>麻
</韻部>
<調>平
</調>
<重紐>
</重紐>
<攝>假
</攝>
</categories>
<yundianwang-reconstructions>
<li-rong>tʃa
</li-rong>
<pan-wuyun>tʂɯa
</pan-wuyun>
<wang-li>tʃa
</wang-li>
<pulleyblank>tʂaɨ
</pulleyblank>
<shao-rongfen>tʃa
</shao-rongfen>
<zhengzhang-shangfang>tʃɣa
</zhengzhang-shangfang>
<karlgren>tʂa
</karlgren>
</yundianwang-reconstructions>
<authorial-reconstructions>
<baxter>tsrae
</baxter>
</authorial-reconstructions>
</middle-chinese>
<old-chinese>
<pan-wuyun>
<yunbu>歌1
</yunbu>
<phonetic>左
</phonetic>
<oc>skraal
</oc>
</pan-wuyun>
<zhengzhang-shangfang>
<oc>shlaal
</oc>
<yunbu>歌1
</yunbu>
<phonetic>左
</phonetic>
<notes>
</notes>
</zhengzhang-shangfang>
</old-chinese>
</pronunciation>
</guangyun-entry>