<?xml version="1.0" encoding="UTF-8"?>
<tls:ann xmlns="http://www.tei-c.org/ns/1.0" xmlns:tls="http://hxwd.org/ns/1.0" concept="OBTAIN" concept-id="uuid-1c8899d4-cf5f-45c4-a4df-32d345c95491" xml:id="uuid-9f8cde0d-2771-4b61-8cde-0d2771db61f0">
    <link target="#KR3c0005_tls_049-2a.6 #uuid-4116d102-a617-4b75-b22e-d8bbc0962905"/>
    <tls:text>
        <tls:srcline title="韓非子" target="#KR3c0005_tls_049-2a.6" pos="3">鑽燧取火</tls:srcline>
        <tls:line title="韓非子 (en)" src="C. Harbsmeier">he drilled the flint stone and made fire</tls:line>
    </tls:text>
    <form corresp="#uuid-ae7faa0b-7337-42ff-bf3e-a4d370dad65d" orig="取">
        <orth>取</orth>
        <pron xml:lang="zh-Latn-x-pinyin">qǔ</pron>
    </form>
    <sense corresp="#uuid-4116d102-a617-4b75-b22e-d8bbc0962905">
        <gramGrp>
                    <pos>V</pos>
  <tls:syn-func corresp="#uuid-fbfb2371-2537-4a99-a876-41b15ec2463c">vtoN</tls:syn-func>
                    <usg type="warring-states-currency">5</usg>
                </gramGrp>
        <def>obtain (something desirable), gain, win; manage to take over occasionally: get as far as (100 miles)</def>
    </sense>
    <tls:metadata resp="#CH" created="2019-03-22T17:15:50.364+09:00">
        <respStmt>
            <resp>added</resp>
            <name>CH</name>
        </respStmt>
    </tls:metadata>
</tls:ann>