<?xml version="1.0" encoding="UTF-8"?>
<tls:ann xmlns="http://www.tei-c.org/ns/1.0" xmlns:tls="http://hxwd.org/ns/1.0" concept="NOBLE" concept-id="uuid-ddb8ae45-16cf-4034-896a-882bbfb664a8" xml:id="uuid-af0857bc-b85e-4482-8857-bcb85e9482a6">
    <link target="#KR3j0080_tls_001-9a.9 #uuid-d0e990af-d55e-491f-b3b2-3306e08b2c60"/>
    <tls:text>
        <tls:srcline title="論衡" target="#KR3j0080_tls_001-9a.9" pos="3">以取尊貴，</tls:srcline>
        <tls:line title="論衡 (en)" src="Hu Chirui and Michael Nylan">and thus obtains high status;</tls:line>
    </tls:text>
    <form corresp="#uuid-29be220c-b19f-4f4a-9bfd-fdbcc657dc22 #uuid-cc274e77-a8ae-4b96-a9eb-d55aa936c165" orig="尊貴">
        <orth>尊貴</orth>
        <pron xml:lang="zh-Latn-x-pinyin">zūn guì</pron>
    </form>
    <sense corresp="#uuid-d0e990af-d55e-491f-b3b2-3306e08b2c60">
        <gramGrp>
                    <pos>N</pos>
  <tls:syn-func corresp="#uuid-9629f093-fa64-4769-9b05-9f49f12c7790">NPab{N1=N2}</tls:syn-func>
  <tls:sem-feat corresp="#uuid-2a66fc1c-6671-47d2-bd04-cfd6ccae64b8">stative</tls:sem-feat>
                    <usg type="warring-states-currency">4</usg>
                </gramGrp>
        <def>general state of nobility</def>
    </sense>
    <tls:metadata resp="#CH" created="2019-03-22T11:15:04.359+09:00">
        <respStmt>
            <resp>added</resp>
            <name>CH</name>
        </respStmt>
    </tls:metadata>
</tls:ann>