<?xml version="1.0" encoding="UTF-8"?>
<tls:ann xmlns="http://www.tei-c.org/ns/1.0" xmlns:tls="http://hxwd.org/ns/1.0" concept="OBTAIN" concept-id="uuid-1c8899d4-cf5f-45c4-a4df-32d345c95491" xml:id="uuid-e77d7e63-0d28-46b6-bd7e-630d28c6b6c3">
    <link target="#KR6b0059_T_005-0382b.61 #uuid-ca1a06ff-8a19-4bba-9108-2ffc95433acb"/>
    <tls:text>
        <tls:srcline title="賢愚經" target="#KR6b0059_T_005-0382b.61" pos="1">獲大珍寶，安隱吉還。</tls:srcline>
        <tls:line title="賢愚經 (en)" src="Sun Xixin and Victor Mair">得到了大量珍寶，平安順利地回來了。</tls:line>
    </tls:text>
    <form corresp="#uuid-25889cfa-8f93-4023-ade8-c26fe1c72a2a" orig="獲">
        <orth>獲</orth>
        <pron xml:lang="zh-Latn-x-pinyin">huò</pron>
    </form>
    <sense corresp="#uuid-ca1a06ff-8a19-4bba-9108-2ffc95433acb">
        <gramGrp>
                    <pos>V</pos>
  <tls:syn-func corresp="#uuid-fbfb2371-2537-4a99-a876-41b15ec2463c">vtoN</tls:syn-func>
                    <usg type="warring-states-currency">2</usg>
                </gramGrp>
        <def>obtain through effort, get hold of</def>
    </sense>
    <tls:metadata resp="#CH" created="2019-03-22T11:15:04.359+09:00">
        <respStmt>
            <resp>added</resp>
            <name>CH</name>
        </respStmt>
    </tls:metadata>
</tls:ann>