<?xml version="1.0" encoding="UTF-8"?>
<tls:ann xmlns="http://www.tei-c.org/ns/1.0" xmlns:tls="http://hxwd.org/ns/1.0" concept="END" concept-id="uuid-d32046d9-2cea-4892-80a2-1bcbcdc1f113" xml:id="343c2c13-d98a-4ff8-bc2c-13d98acff89b">
    <link target="#KR4a0001_tls_004-27a.17 #uuid-4de72ff4-a991-49fe-ad08-08b763ca1334"/>
    <tls:text>
        <tls:srcline title="楚辭" target="#KR4a0001_tls_004-27a.17" pos="1">限之以大故。</tls:srcline>
        <tls:line title="楚辭 (en)">And end it all in the Great End.</tls:line>
    </tls:text>
    <form corresp="#uuid-bb862897-05f8-45ef-acd4-9d17b05d33a6">
        <orth>限</orth>
        <pron xml:lang="zh-Latn-x-pinyin">xiàn</pron>
    </form>
    <sense corresp="#uuid-4de72ff4-a991-49fe-ad08-08b763ca1334">
        <gramGrp>
                    <pos>V</pos>
  <tls:syn-func corresp="#uuid-fbfb2371-2537-4a99-a876-41b15ec2463c">vtoN</tls:syn-func>
                    <usg type="warring-states-currency">3</usg>
                </gramGrp>
        <def>put an end to</def>
    </sense>
    <tls:metadata resp="#CH" created="2019-03-17T11:45:43.347+09:00">
        <respStmt>
            <resp>added</resp>
            <name>CH</name>
        </respStmt>
    </tls:metadata>
</tls:ann>