<?xml version="1.0" encoding="UTF-8"?>
<tls:ann xmlns="http://www.tei-c.org/ns/1.0" xmlns:tls="http://hxwd.org/ns/1.0" concept="KILL" concept-id="uuid-16de396a-482f-44f4-bc0a-dd073c887f9b" xml:id="uuid-d5d848fe-5175-4825-9848-fe5175c82522">
    <link target="#KR1e0001_tls_007-107a.9 #uuid-b8f73d19-d283-4527-b6ae-32d0e229feae"/>
    <tls:text>
        <tls:srcline title="春秋左傳" target="#KR1e0001_tls_007-107a.9" pos="3">將可殪也。</tls:srcline>
        <tls:line title="春秋左傳 (en)" src="Legge">and then he may be utterly destroyed.</tls:line>
    </tls:text>
    <form corresp="#uuid-4bdeca56-9e6f-419a-8a6c-ab9c080bdab5" orig="殪">
        <orth>殪</orth>
        <pron xml:lang="zh-Latn-x-pinyin">yì</pron>
    </form>
    <sense corresp="#uuid-b8f73d19-d283-4527-b6ae-32d0e229feae">
        <gramGrp>
                    <pos>V</pos>
  <tls:syn-func corresp="#uuid-fbfb2371-2537-4a99-a876-41b15ec2463c">vtoN</tls:syn-func>
  <tls:sem-feat corresp="#uuid-988c2bcf-3cdd-4b9e-b8a4-615fe3f7f81e">passive</tls:sem-feat>
                </gramGrp>
        <def>get killed</def>
    </sense>
    <tls:metadata resp="#CH" created="2019-03-22T17:15:50.364+09:00">
        <respStmt>
            <resp>added</resp>
            <name>CH</name>
        </respStmt>
    </tls:metadata>
</tls:ann>