<?xml version="1.0" encoding="UTF-8"?>
<tls:ann xmlns="http://www.tei-c.org/ns/1.0" xmlns:tls="http://hxwd.org/ns/1.0" concept="SLANDER" concept-id="uuid-f28f17dd-220d-4410-813a-811361c4a269" xml:id="45040111-780e-4947-8401-11780ef94753">
    <link target="#KR1e0001_tls_010-492a.64 #uuid-ee10b6c9-4cfd-4e6b-b37d-a06b2e6934ea"/>
    <tls:text>
        <tls:srcline title="春秋左傳" target="#KR1e0001_tls_010-492a.64" pos="4">不思謗讟，
                    </tls:srcline>
        <tls:line title="春秋左傳 (en)">giving no thought to the maledictions of the people,</tls:line>
    </tls:text>
    <form corresp="#uuid-8ece4dc5-947f-4e2f-b08d-edff7d39250d">
        <orth>讟</orth>
        <pron xml:lang="zh-Latn-x-pinyin">dú</pron>
    </form>
    <sense corresp="#uuid-ee10b6c9-4cfd-4e6b-b37d-a06b2e6934ea">
        <gramGrp>
                    <pos>N</pos>
  <tls:syn-func corresp="#uuid-76be1df4-3d73-4e5f-bbc2-729542645bc8">nab</tls:syn-func>
  <tls:sem-feat corresp="#uuid-f55cff2f-f0e3-4f08-a89c-5d08fcf3fe89">act</tls:sem-feat>
                    <usg type="warring-states-currency">2</usg>
                </gramGrp>
        <def>backbiting; slanderous talk</def>
    </sense>
    <tls:metadata resp="#CH" created="2019-03-17T11:45:43.347+09:00">
        <respStmt>
            <resp>added</resp>
            <name>CH</name>
        </respStmt>
    </tls:metadata>
</tls:ann>