<?xml version="1.0" encoding="UTF-8"?>
<tls:ann xmlns="http://www.tei-c.org/ns/1.0" xmlns:tls="http://hxwd.org/ns/1.0" concept="PLAN" concept-id="uuid-8bed01e5-7f3e-47ee-8296-6f90c3f31f37" xml:id="uuid-c1e35d6e-0013-4827-a35d-6e0013582709">
    <link target="#KR3c0005_tls_026-13a.7 #uuid-ef2dea45-81bb-43ad-964a-80f9ec47c96e"/>
    <tls:text>
        <tls:srcline title="韓非子" target="#KR3c0005_tls_026-13a.7" pos="5">孫、吳之略廢，</tls:srcline>
        <tls:line title="韓非子 (en)" src="C. Harbsmeier">Sūnzǐ's and Wúzǐ's strategies were abandoned</tls:line>
    </tls:text>
    <form corresp="#uuid-5e347af4-858f-4384-88f1-3a4dfa37f8ab" orig="略">
        <orth>略</orth>
        <pron xml:lang="zh-Latn-x-pinyin">lǜe</pron>
    </form>
    <sense corresp="#uuid-ef2dea45-81bb-43ad-964a-80f9ec47c96e">
        <gramGrp>
                    <pos>N</pos>
  <tls:syn-func corresp="#uuid-76be1df4-3d73-4e5f-bbc2-729542645bc8">nab</tls:syn-func>
  <tls:sem-feat corresp="#uuid-98e7674b-b362-466f-9568-d0c14470282a">psych</tls:sem-feat>
                </gramGrp>
        <def>strategy; plan</def>
    </sense>
    <tls:metadata resp="#CH" created="2019-03-22T17:15:50.364+09:00">
        <respStmt>
            <resp>added</resp>
            <name>CH</name>
        </respStmt>
    </tls:metadata>
</tls:ann>