<?xml version="1.0" encoding="UTF-8"?>
<tls:ann xmlns="http://www.tei-c.org/ns/1.0" xmlns:tls="http://hxwd.org/ns/1.0" concept="INTENSELY" concept-id="uuid-bdfb27cd-d480-466a-a54f-e011967ed13e" xml:id="uuid-5a8cd751-1521-4143-8cd7-511521d1434d">
    <link target="#KR1e0001_tls_009-180a.4 #uuid-a2eae503-9bd4-4594-b1d4-7ff528cbd0db"/>
    <tls:text>
        <tls:srcline title="春秋左傳" target="#KR1e0001_tls_009-180a.4" pos="4">『謀夫孔多，</tls:srcline>
        <tls:line title="春秋左傳 (en)" src="Legge">'The counsellors are very many,</tls:line>
    </tls:text>
    <form corresp="#uuid-c171d3e9-57c2-4d17-bd27-4cddbbd7f32d" orig="孔">
        <orth>孔</orth>
        <pron xml:lang="zh-Latn-x-pinyin">kǒng</pron>
    </form>
    <sense corresp="#uuid-a2eae503-9bd4-4594-b1d4-7ff528cbd0db">
        <gramGrp>
                    <pos>V</pos>
  <tls:syn-func corresp="#uuid-2a0ded86-3b04-4488-bb7a-3efccfa35844">vadV</tls:syn-func>
                    <usg type="warring-states-currency">2</usg>
                </gramGrp>
        <def>poetic: extremely</def>
    </sense>
    <tls:metadata resp="#CH" created="2019-03-22T11:15:04.359+09:00">
        <respStmt>
            <resp>added</resp>
            <name>CH</name>
        </respStmt>
    </tls:metadata>
</tls:ann>