<?xml version="1.0" encoding="UTF-8"?>
<tls:ann xmlns="http://www.tei-c.org/ns/1.0" xmlns:tls="http://hxwd.org/ns/1.0" concept="IMAGINATION" concept-id="uuid-c280ecf9-7d06-4758-ac54-f4a2c2306598" xml:id="uuid-1a414962-e9f9-42df-8149-62e9f992df47">
    <link target="#KR4a0001_tls_005-8a.44 #uuid-141acd3e-dd7c-4641-83f3-a606960cc252"/>
    <tls:text>
        <tls:srcline title="楚辭" target="#KR4a0001_tls_005-8a.44" pos="5">思舊故以想像兮，</tls:srcline>
        <tls:line title="楚辭 (en)" src="HAWKES 1985 ">135 I pictured my dear ones in imagination,</tls:line>
    </tls:text>
    <form corresp="#uuid-50561efa-ffdc-475c-b16b-e82d295d010e #uuid-546c3004-cc68-4595-9d2a-43f09ff362b7" orig="想像">
        <orth>想像</orth>
        <pron xml:lang="zh-Latn-x-pinyin">xiǎng xiàng</pron>
    </form>
    <sense corresp="#uuid-141acd3e-dd7c-4641-83f3-a606960cc252">
        <gramGrp>
                    <pos>V</pos>
  <tls:syn-func corresp="#uuid-98f2ce75-ae37-4667-90ff-f418c4aeaa33">VPtoN</tls:syn-func>
                </gramGrp>
        <def>imagine</def>
    </sense>
    <tls:metadata resp="#CH" created="2019-03-23T21:01:49.895+09:00">
        <respStmt>
            <resp>added</resp>
            <name>CH</name>
        </respStmt>
    </tls:metadata>
</tls:ann>