<?xml version="1.0" encoding="UTF-8"?>
<tls:ann xmlns="http://www.tei-c.org/ns/1.0" xmlns:tls="http://hxwd.org/ns/1.0" concept="LEAD" concept-id="uuid-70cd50b6-aa7d-4ffd-b4d1-55dfc2b46d02" xml:id="bf77b08c-4bea-4379-b7b0-8c4beac379e9">
    <link target="#KR6b0066_T_003-0552c.71 #uuid-052cacc6-ee10-4293-955f-4a8b8a962c70"/>
    <tls:text>
        <tls:srcline title="百喻經" target="#KR6b0066_T_003-0552c.71" pos="1">驅向彼國。</tls:srcline>
        <tls:line title="百喻經 (en)">and hastened towards the capital.</tls:line>
    </tls:text>
    <form corresp="#uuid-309f5378-3d9c-4dbe-9ab3-e4372a465965">
        <orth>驅</orth>
        <pron xml:lang="zh-Latn-x-pinyin">qū</pron>
    </form>
    <sense corresp="#uuid-052cacc6-ee10-4293-955f-4a8b8a962c70">
        <gramGrp>
                    <pos>V</pos>
  <tls:syn-func corresp="#uuid-e64a7a95-b54b-4c94-9d6d-f55dbf079701">vt(oN)</tls:syn-func>
                </gramGrp>
        <def>drive, steer; lead (cattle in a direction)</def>
    </sense>
    <tls:metadata resp="#CH" created="2019-03-17T11:45:43.347+09:00">
        <respStmt>
            <resp>added</resp>
            <name>CH</name>
        </respStmt>
    </tls:metadata>
</tls:ann>