<?xml version="1.0" encoding="UTF-8"?>
<tls:ann xmlns="http://www.tei-c.org/ns/1.0" xmlns:tls="http://hxwd.org/ns/1.0" concept="STATE" concept-id="uuid-723efc5a-352b-43ce-b8eb-e92ff5302db9" xml:id="8ff073df-aa12-4a7a-b073-dfaa12fa7aee">
    <link target="#KR1h0001_tls_003-37a.16 #uuid-2d58abf2-955a-447d-8098-ede2ae9da613"/>
    <tls:text>
        <tls:srcline title="孟子" target="#KR1h0001_tls_003-37a.16" pos="3">則鄰國之民仰之若父母矣。
                    </tls:srcline>
        <tls:line title="孟子 (en)">then the people of neighbouning states will look up to him as (they are looking up) to their parents.</tls:line>
    </tls:text>
    <form corresp="#uuid-ba086483-4a6c-43de-800a-e37e8258b43a">
        <orth>國</orth>
        <pron xml:lang="zh-Latn-x-pinyin">guó</pron>
    </form>
    <sense corresp="#uuid-2d58abf2-955a-447d-8098-ede2ae9da613">
        <gramGrp>
                    <pos>N</pos>
  <tls:syn-func corresp="#uuid-b6da65fd-429f-4245-9f94-a22078cc0512">ncc</tls:syn-func>
                    <usg type="warring-states-currency">5</usg>
                </gramGrp>
        <def>(not necessarily large, territorially conceived) state (within the empire)</def>
    </sense>
    <tls:metadata resp="#CH" created="2019-03-17T11:45:43.347+09:00">
        <respStmt>
            <resp>added</resp>
            <name>CH</name>
        </respStmt>
    </tls:metadata>
</tls:ann>