<?xml version="1.0" encoding="UTF-8"?>
<tls:ann xmlns="http://www.tei-c.org/ns/1.0" xmlns:tls="http://hxwd.org/ns/1.0" concept="DUST" concept-id="uuid-33c110e0-d2f6-41f0-be53-a74361ee3f69" xml:id="e5d16e17-dbb1-4bed-916e-17dbb14bedae">
    <link target="#KR5c0126_tls_005-4a.22 #uuid-53301a7a-f93e-40b9-91b3-b5cb22cc38c8"/>
    <tls:text>
        <tls:srcline title="莊子" target="#KR5c0126_tls_005-4a.22" pos="6">『鑑明則塵垢不止，
                    </tls:srcline>
        <tls:line title="莊子 (en)">that if the mirror is bright, no dust settles on it;</tls:line>
    </tls:text>
    <form corresp="#uuid-86d42ba3-024e-413f-b98b-83fbeee99c93">
        <orth>垢</orth>
        <pron xml:lang="zh-Latn-x-pinyin">gòu</pron>
    </form>
    <sense corresp="#uuid-53301a7a-f93e-40b9-91b3-b5cb22cc38c8">
        <gramGrp>
                    <pos>N</pos>
  <tls:syn-func corresp="#uuid-e917a78b-5500-4276-a5fe-156b8bdecb7b">nm</tls:syn-func>
                </gramGrp>
        <def>dirt, dust</def>
    </sense>
    <tls:metadata resp="#CH" created="2019-03-17T11:45:43.347+09:00">
        <respStmt>
            <resp>added</resp>
            <name>CH</name>
        </respStmt>
    </tls:metadata>
</tls:ann>