<?xml version="1.0" encoding="UTF-8"?>
<tls:ann xmlns="http://www.tei-c.org/ns/1.0" xmlns:tls="http://hxwd.org/ns/1.0" concept="GIVE" concept-id="uuid-ed1aeb49-abff-4167-a18e-60c0f2202d63" xml:id="uuid-3f528056-1aa4-4bb8-9280-561aa4ebb873">
    <link target="#KR3c0005_tls_023-68a.10 #uuid-168c7f62-2e2e-495b-8e33-f2a27f70252c"/>
    <tls:text>
        <tls:srcline title="韓非子" target="#KR3c0005_tls_023-68a.10" pos="6">以鍊金百鎰遺晉。</tls:srcline>
        <tls:line title="韓非子 (en)" src="C. Harbsmeier">and he gave one hundred taels of purified gold as a present to Jìn.</tls:line>
    </tls:text>
    <form corresp="#uuid-98743eb1-5548-47b9-b51c-ce15f3a2fcb8" orig="遺">
        <orth>遺</orth>
        <pron xml:lang="zh-Latn-x-pinyin">wèi</pron>
    </form>
    <sense corresp="#uuid-168c7f62-2e2e-495b-8e33-f2a27f70252c">
        <gramGrp>
                    <pos>V</pos>
  <tls:syn-func corresp="#uuid-b1da1095-72d1-4dc8-bd0c-f66788b53021">vttoN1:postvtoN2</tls:syn-func>
                    <usg type="warring-states-currency">3</usg>
                </gramGrp>
        <def>give N2 to N1</def>
    </sense>
    <tls:metadata resp="#CH" created="2019-03-22T17:15:50.364+09:00">
        <respStmt>
            <resp>added</resp>
            <name>CH</name>
        </respStmt>
    </tls:metadata>
</tls:ann>