<?xml version="1.0" encoding="UTF-8"?>
<tls:ann xmlns="http://www.tei-c.org/ns/1.0" xmlns:tls="http://hxwd.org/ns/1.0" concept="GENITIVE PARTICLES" concept-id="uuid-8ffa4531-1f93-473b-b468-7d0cf9390af1" xml:id="uuid-64b102ab-65e1-43ec-b102-ab65e113ec82">
    <link target="#KR1h0001_tls_002-40a.3 #uuid-72da60e6-6960-45e3-b0db-260b95878602"/>
    <tls:text>
        <tls:srcline title="孟子" target="#KR1h0001_tls_002-40a.3" pos="3">「王之臣有託其妻子於其友</tls:srcline>
        <tls:line title="孟子 (en)" src="David Sehnal; D.C. Lau">Supposing amoung your subjects there was such one, who entrusted his wife and children to his friend</tls:line>
    </tls:text>
    <form corresp="#uuid-dd2ad4ab-7266-4ee9-a622-5790a96a6515" orig="之">
        <orth>之</orth>
        <pron xml:lang="zh-Latn-x-pinyin">zhī</pron>
    </form>
    <sense corresp="#uuid-72da60e6-6960-45e3-b0db-260b95878602">
        <gramGrp>
                    <pos/>
  <tls:syn-func corresp="#uuid-db3e24ed-d18b-454f-9f8f-47822681721b">npropostN1.adN2</tls:syn-func>
  <tls:sem-feat corresp="#uuid-69b401a4-7fa0-4d82-8a37-dea2761bbc79">genitive</tls:sem-feat>
                </gramGrp>
        <def>NP1 owns, controls or employs NP2 三家之堂</def>
    </sense>
    <tls:metadata resp="#CH" created="2019-03-22T17:15:50.364+09:00">
        <respStmt>
            <resp>added</resp>
            <name>CH</name>
        </respStmt>
    </tls:metadata>
</tls:ann>