<?xml version="1.0" encoding="UTF-8"?>
<tls:ann xmlns="http://www.tei-c.org/ns/1.0" xmlns:tls="http://hxwd.org/ns/1.0" concept="COLD" concept-id="uuid-761ae21c-3456-4f23-90b6-6f38c842f6fc" xml:id="uuid-a757ef6c-2ec7-4c21-97ef-6c2ec78c21af">
    <link target="#KR3c0005_tls_020-138a.3 #uuid-57a6ac28-6879-4f85-87b3-06828f1d6491"/>
    <tls:text>
        <tls:srcline title="韓非子" target="#KR3c0005_tls_020-138a.3" pos="6">「冬日之閉凍也不固，</tls:srcline>
        <tls:line title="韓非子 (en)" src="C. Harbsmeier">"If during winter days one does not firmly seal things off against the frost</tls:line>
    </tls:text>
    <form corresp="#uuid-6d97acce-82c7-497e-8e1d-00bb94944a66" orig="凍">
        <orth>凍</orth>
        <pron xml:lang="zh-Latn-x-pinyin">dòng</pron>
    </form>
    <sense corresp="#uuid-57a6ac28-6879-4f85-87b3-06828f1d6491">
        <gramGrp>
                    <pos>N</pos>
  <tls:syn-func corresp="#uuid-76be1df4-3d73-4e5f-bbc2-729542645bc8">nab</tls:syn-func>
  <tls:sem-feat corresp="#uuid-2a66fc1c-6671-47d2-bd04-cfd6ccae64b8">stative</tls:sem-feat>
                    <usg type="warring-states-currency">4</usg>
                </gramGrp>
        <def>frost</def>
    </sense>
    <tls:metadata resp="#CH" created="2019-03-23T21:01:49.895+09:00">
        <respStmt>
            <resp>added</resp>
            <name>CH</name>
        </respStmt>
    </tls:metadata>
</tls:ann>