<?xml version="1.0" encoding="UTF-8"?>
<tls:ann xmlns="http://www.tei-c.org/ns/1.0" xmlns:tls="http://hxwd.org/ns/1.0" concept="RALLY" concept-id="uuid-dcc38429-471a-4f41-aaa2-a22659487ac0" xml:id="uuid-38165935-e44e-4f60-9659-35e44edf605b">
    <link target="#KR6b0059_T_001-0351c.45 #uuid-5976786c-cd59-4fab-948b-c3f0cc6a5285"/>
    <tls:text>
        <tls:srcline title="賢愚經" target="#KR6b0059_T_001-0351c.45" pos="3">宜往投歸，</tls:srcline>
        <tls:line title="賢愚經 (en)" src="Sun Xixin and Victor Mair">你應該投奔歸順他，</tls:line>
    </tls:text>
    <form corresp="#uuid-0174354e-3eea-49d7-a9d6-d3040cca221f #uuid-f92bd229-a310-48c4-8739-f679500d0958" orig="投歸">
        <orth>投歸</orth>
        <pron xml:lang="zh-Latn-x-pinyin">tóu guī</pron>
    </form>
    <sense corresp="#uuid-5976786c-cd59-4fab-948b-c3f0cc6a5285">
        <gramGrp>
                    <pos>V</pos>
  <tls:syn-func corresp="#uuid-5b3376f4-75c4-4047-94eb-fc6d1bca520d">VPt(oN)</tls:syn-func>
                </gramGrp>
        <def>rally to and join a contextually determinate person</def>
    </sense>
    <tls:metadata resp="#CH" created="2019-03-22T17:15:50.364+09:00">
        <respStmt>
            <resp>added</resp>
            <name>CH</name>
        </respStmt>
    </tls:metadata>
</tls:ann>