<?xml version="1.0" encoding="UTF-8"?>
<tls:ann xmlns="http://www.tei-c.org/ns/1.0" xmlns:tls="http://hxwd.org/ns/1.0" concept="OLD" concept-id="uuid-bcf8bcdd-f03c-4eca-a77a-7cb184c1bbc1" xml:id="296bfcc3-6509-49e9-abfc-c3650949e9ce">
    <link target="#KR3c0001_tls_018-5a.7 #uuid-3407b188-8d27-46e6-a10f-925c34144d08"/>
    <tls:text>
        <tls:srcline title="管子" target="#KR3c0001_tls_018-5a.7" pos="4 5">此之謂老老。
                    </tls:srcline>
        <tls:line title="管子 (en)">This is what is meant by "honoring the elderly."778</tls:line>
    </tls:text>
    <form corresp="#uuid-64f3232a-4076-45ea-889b-9704df07af94">
        <orth>老</orth>
        <pron xml:lang="zh-Latn-x-pinyin">lǎo</pron>
    </form>
    <sense corresp="#uuid-3407b188-8d27-46e6-a10f-925c34144d08">
        <gramGrp>
                    <pos>V</pos>
  <tls:syn-func corresp="#uuid-fbfb2371-2537-4a99-a876-41b15ec2463c">vtoN</tls:syn-func>
  <tls:sem-feat corresp="#uuid-1ddeb9e4-67de-4466-b517-24cfd829f3de">N=hum</tls:sem-feat>
                    <usg type="warring-states-currency">3</usg>
                </gramGrp>
        <def>to treat somebody in the way the old people should be treated</def>
    </sense>
    <tls:metadata resp="#CH" created="2019-03-17T11:45:43.347+09:00">
        <respStmt>
            <resp>added</resp>
            <name>CH</name>
        </respStmt>
    </tls:metadata>
</tls:ann>