<?xml version="1.0" encoding="UTF-8"?>
<tls:ann xmlns="http://www.tei-c.org/ns/1.0" xmlns:tls="http://hxwd.org/ns/1.0" concept="TAX" concept-id="uuid-ab5f4647-14ee-40bf-a3f5-a4e8db993b50" xml:id="uuid-35049e37-50eb-4dac-849e-3750eb7dac03">
    <link target="#KR3c0005_tls_009-9a.4 #uuid-b58bb3b3-c3fe-4100-a4ce-067acb8c9afe"/>
    <tls:text>
        <tls:srcline title="韓非子" target="#KR3c0005_tls_009-9a.4" pos="2">重賦斂</tls:srcline>
        <tls:line title="韓非子 (en)" src="C. Harbsmeier">they will increase taxes and levies</tls:line>
    </tls:text>
    <form corresp="#uuid-066eb596-0439-47dc-a114-d3c58d48b83f #uuid-8cb01d93-d62f-4fc9-9757-4d03a0dc48a4" orig="賦斂">
        <orth>賦斂</orth>
        <pron xml:lang="zh-Latn-x-pinyin">fù liǎn</pron>
    </form>
    <sense corresp="#uuid-b58bb3b3-c3fe-4100-a4ce-067acb8c9afe">
        <gramGrp>
                    <pos>N</pos>
  <tls:syn-func corresp="#uuid-db0698e7-db2f-4ee3-9a20-0c2b2e0cebf0">NPab</tls:syn-func>
  <tls:sem-feat corresp="#uuid-2ef405b2-627b-4f29-940b-848d5428e30e">social</tls:sem-feat>
                </gramGrp>
        <def>all sorts of taxes</def>
    </sense>
    <tls:metadata resp="#CH" created="2019-03-23T21:01:49.895+09:00">
        <respStmt>
            <resp>added</resp>
            <name>CH</name>
        </respStmt>
    </tls:metadata>
</tls:ann>