<?xml version="1.0" encoding="UTF-8"?>
<tls:ann xmlns="http://www.tei-c.org/ns/1.0" xmlns:tls="http://hxwd.org/ns/1.0" concept="CHOOSE" concept-id="uuid-e8c0bafd-4166-403c-af11-7a5b5d318af5" xml:id="uuid-0bff24b1-8b04-49f2-bf24-b18b04d9f247">
    <link target="#KR1d0052_tls_009-1a.18 #uuid-c5fd4c87-3216-4138-afd3-7a7bd95b8dbc"/>
    <tls:text>
        <tls:srcline title="禮記" target="#KR1d0052_tls_009-1a.18" pos="1">選賢與能，</tls:srcline>
        <tls:line title="禮記 (en)" src="Legge">they chose men of talents, virtue and ability;</tls:line>
    </tls:text>
    <form corresp="#uuid-bdaabb0f-6177-4c5c-8497-1b917ecdf21e" orig="選">
        <orth>選</orth>
        <pron xml:lang="zh-Latn-x-pinyin">xuǎn</pron>
    </form>
    <sense corresp="#uuid-c5fd4c87-3216-4138-afd3-7a7bd95b8dbc">
        <gramGrp>
                    <pos>V</pos>
  <tls:syn-func corresp="#uuid-fbfb2371-2537-4a99-a876-41b15ec2463c">vtoN</tls:syn-func>
                    <usg type="warring-states-currency">4</usg>
                </gramGrp>
        <def>pick out according to quality, select and appoint</def>
    </sense>
    <tls:metadata resp="#CH" created="2019-03-23T21:01:49.895+09:00">
        <respStmt>
            <resp>added</resp>
            <name>CH</name>
        </respStmt>
    </tls:metadata>
</tls:ann>