<?xml version="1.0" encoding="UTF-8"?>
<tls:ann xmlns="http://www.tei-c.org/ns/1.0" xmlns:tls="http://hxwd.org/ns/1.0" concept="BATTLE ARRAY" concept-id="uuid-e85f3767-f78a-4678-aca7-2aead905c2fa" xml:id="b2fe4538-097c-4221-be45-38097ce2212b">
    <link target="#KR1e0001_tls_009-614a.19 #uuid-764f97ae-413e-46a6-9e83-2cf507f65fdb"/>
    <tls:text>
        <tls:srcline title="春秋左傳" target="#KR1e0001_tls_009-614a.19" pos="1">陳以待我。
                    </tls:srcline>
        <tls:line title="春秋左傳 (en)">in order to wait for the result.</tls:line>
    </tls:text>
    <form corresp="#uuid-c947bb27-b226-460f-b268-79d4b7c857b0">
        <orth>陳</orth>
        <pron xml:lang="zh-Latn-x-pinyin">zhèn</pron>
    </form>
    <sense corresp="#uuid-764f97ae-413e-46a6-9e83-2cf507f65fdb">
        <gramGrp>
                    <pos>V</pos>
  <tls:syn-func corresp="#uuid-c20780b3-41f9-491b-bb61-a269c1c4b48f">vi</tls:syn-func>
  <tls:sem-feat corresp="#uuid-f55cff2f-f0e3-4f08-a89c-5d08fcf3fe89">act</tls:sem-feat>
                </gramGrp>
        <def>line up in battle array</def>
    </sense>
    <tls:metadata resp="#CH" created="2019-03-17T11:45:43.347+09:00">
        <respStmt>
            <resp>added</resp>
            <name>CH</name>
        </respStmt>
    </tls:metadata>
</tls:ann>