<?xml version="1.0" encoding="UTF-8"?>
<tls:ann xmlns="http://www.tei-c.org/ns/1.0" xmlns:tls="http://hxwd.org/ns/1.0" concept="SLANDER" concept-id="uuid-f28f17dd-220d-4410-813a-811361c4a269" xml:id="uuid-a491f8fb-4279-4445-91f8-fb4279a44580">
    <link target="#KR1e0001_tls_009-84a.39 #uuid-bd8d2b77-a373-4a25-ae41-d2566542ddda"/>
    <tls:text>
        <tls:srcline title="春秋左傳" target="#KR1e0001_tls_009-84a.39" pos="5">伯明氏之讒子弟也，</tls:srcline>
        <tls:line title="春秋左傳 (en)" src="Legge">was a slanderous scion of the House of Pih-ming,</tls:line>
    </tls:text>
    <form corresp="#uuid-6fa719da-45fd-473b-87c3-3717ebb18a4e" orig="讒">
        <orth>讒</orth>
        <pron xml:lang="zh-Latn-x-pinyin">chán</pron>
    </form>
    <sense corresp="#uuid-bd8d2b77-a373-4a25-ae41-d2566542ddda">
        <gramGrp>
                    <pos>V</pos>
  <tls:syn-func corresp="#uuid-fed035db-e7bd-4d23-bd05-9698b26e38f9">vadN</tls:syn-func>
                    <usg type="warring-states-currency">2</usg>
                </gramGrp>
        <def>slanderous, slandering 讒人</def>
    </sense>
    <tls:metadata resp="#CH" created="2019-03-22T17:15:50.364+09:00">
        <respStmt>
            <resp>added</resp>
            <name>CH</name>
        </respStmt>
    </tls:metadata>
</tls:ann>